odoo/addons/partner_contact_role/README.rst
odoo/addons/partner_contact_role/__init__.py
odoo/addons/partner_contact_role/__manifest__.py
odoo/addons/partner_contact_role/i18n/es.po
odoo/addons/partner_contact_role/i18n/fr.po
odoo/addons/partner_contact_role/i18n/it.po
odoo/addons/partner_contact_role/i18n/partner_contact_role.pot
odoo/addons/partner_contact_role/models/__init__.py
odoo/addons/partner_contact_role/models/res_partner.py
odoo/addons/partner_contact_role/readme/CONFIGURE.md
odoo/addons/partner_contact_role/readme/CONTRIBUTORS.md
odoo/addons/partner_contact_role/readme/CREDITS.md
odoo/addons/partner_contact_role/readme/DESCRIPTION.md
odoo/addons/partner_contact_role/readme/USAGE.md
odoo/addons/partner_contact_role/security/ir.model.access.csv
odoo/addons/partner_contact_role/static/description/icon.png
odoo/addons/partner_contact_role/static/description/index.html
odoo/addons/partner_contact_role/views/res_partner.xml
odoo/addons/partner_contact_role/views/res_partner_role.xml
odoo_addon_partner_contact_role-18.0.1.0.0.3.dist-info/METADATA
odoo_addon_partner_contact_role-18.0.1.0.0.3.dist-info/WHEEL
odoo_addon_partner_contact_role-18.0.1.0.0.3.dist-info/top_level.txt
odoo_addon_partner_contact_role-18.0.1.0.0.3.dist-info/RECORD
